py.typed
mistral_dev/__init__.py
mistral_dev/_hooks/__init__.py
mistral_dev/_hooks/registration.py
mistral_dev/_hooks/sdkhooks.py
mistral_dev/_hooks/types.py
mistral_dev/basesdk.py
mistral_dev/chat.py
mistral_dev/embeddings.py
mistral_dev/files.py
mistral_dev/fim.py
mistral_dev/fine_tuning.py
mistral_dev/httpclient.py
mistral_dev/models/__init__.py
mistral_dev/models/badrequest.py
mistral_dev/models/chatcompletionchoices.py
mistral_dev/models/chatcompletionchoicesevent.py
mistral_dev/models/chatcompletionevent.py
mistral_dev/models/chatcompletionrequest.py
mistral_dev/models/chatcompletionrequestjsonmode.py
mistral_dev/models/chatcompletionresponse.py
mistral_dev/models/chatcompletionresponsefunctioncall.py
mistral_dev/models/chatcompletionresponsejsonmode.py
mistral_dev/models/chatcompletionresponsestreamchoice.py
mistral_dev/models/chatcompletionrole.py
mistral_dev/models/chatcompletionsentinelevent.py
mistral_dev/models/chatcompletionstreamrequest.py
mistral_dev/models/chatfunctioncall.py
mistral_dev/models/checkpointout.py
mistral_dev/models/createchatcompletionop.py
mistral_dev/models/deletefileout.py
mistral_dev/models/deltamessage.py
mistral_dev/models/detailedjobout.py
mistral_dev/models/embeddingrequest.py
mistral_dev/models/embeddingresponse.py
mistral_dev/models/eventout.py
mistral_dev/models/files_api_routes_delete_fileop.py
mistral_dev/models/files_api_routes_retrieve_fileop.py
mistral_dev/models/fileschema.py
mistral_dev/models/fimcompletionrequest.py
mistral_dev/models/fimcompletionresponse.py
mistral_dev/models/finetuneablemodel.py
mistral_dev/models/finishreason.py
mistral_dev/models/forbidden.py
mistral_dev/models/functioncall.py
mistral_dev/models/internalservererror.py
mistral_dev/models/jobin.py
mistral_dev/models/jobout.py
mistral_dev/models/jobs_api_routes_fine_tuning_cancel_fine_tuning_jobop.py
mistral_dev/models/jobs_api_routes_fine_tuning_get_fine_tuning_jobop.py
mistral_dev/models/jobs_api_routes_fine_tuning_get_fine_tuning_jobsop.py
mistral_dev-0.5.4a0.dist-info/METADATA
mistral_dev-0.5.4a0.dist-info/WHEEL
mistral_dev-0.5.4a0.dist-info/RECORD
